<?xml version="1.0"?>
<PagePortable xmlns:xsi="http://www.w3.org/2001/XMLSchema-instance" xmlns:xsd="http://www.w3.org/2001/XMLSchema">
  <Title>Filtro de registros</Title>
  <Url>~/SiteSettings/RecordsFilter/Form.aspx</Url>
  <AutoGenerated>true</AutoGenerated>
  <EntityPermissionId />
  <TemplateId />
  <Details />
  <Id>RECORDSFILTERPAGEFORM</Id>
  <Level>Tecnologia</Level>
  <CodeFile />
  <CodeInherits>Benner.Tecnologia.Wes.Components.WebApp.FilterFormPage</CodeInherits>
  <Widgets>
    <PageWidgetPortable>
      <Id>WIDGETID_635925990979239001</Id>
      <Title>Filtro de registros</Title>
      <Order>50</Order>
      <ShowTitle>true</ShowTitle>
      <PortletCssClass />
      <FontIcon />
      <Subtitle />
      <ChromeState>Normal</ChromeState>
      <PortletLayout>Default</PortletLayout>
      <WidgetTypeId>AjaxForm</WidgetTypeId>
      <BootstrapCols>12</BootstrapCols>
      <XmlAttributes><![CDATA[<AjaxFormAttributes>
  <CanDelete>true</CanDelete>
  <CanUpdate>true</CanUpdate>
  <CanInsert>true</CanInsert>
  <EntityViewName>Z_FILTROS.FORM</EntityViewName>
  <FormMode>1</FormMode>
  <IncludeRecordInRecentItems>true</IncludeRecordInRecentItems>
  <UserDefinedCommandsVisible>true</UserDefinedCommandsVisible>
</AjaxFormAttributes>
]]></XmlAttributes>
      <Level>Tecnologia</Level>
    </PageWidgetPortable>
    <PageWidgetPortable>
      <Id>WIDGETID_635926183215682891</Id>
      <MasterWidgetId>WIDGETID_635925990979239001</MasterWidgetId>
      <Title>Condições</Title>
      <Order>100</Order>
      <ShowTitle>true</ShowTitle>
      <PortletCssClass />
      <FontIcon />
      <Subtitle />
      <ChromeState>Normal</ChromeState>
      <PortletLayout>Default</PortletLayout>
      <WidgetTypeId>SimpleGrid</WidgetTypeId>
      <BootstrapCols>12</BootstrapCols>
      <XmlAttributes><![CDATA[<SimpleGridAttributes>
  <CanDelete>false</CanDelete>
  <CanUpdate>false</CanUpdate>
  <CanInsert>false</CanInsert>
  <EntityViewName>Z_FILTROCONDICOES.GRID</EntityViewName>
  <Mode>0</Mode>
  <UserDefinedSelectColumnVisible>false</UserDefinedSelectColumnVisible>
  <UserDefinedPageSize>10</UserDefinedPageSize>
  <SystemFilterOnly>false</SystemFilterOnly>
  <DisplayRowCommand>true</DisplayRowCommand>
  <CompanyFilterMode>1</CompanyFilterMode>
  <UserDefinedCriteriaWhereClause>A.FILTRO = @CAMPO(HANDLE)</UserDefinedCriteriaWhereClause>
  <UserDefinedDisableRowSelection>false</UserDefinedDisableRowSelection>
</SimpleGridAttributes>
]]></XmlAttributes>
      <Level>Tecnologia</Level>
    </PageWidgetPortable>
  </Widgets>
  <Resources />
</PagePortable>