<?xml version="1.0"?>
<PagePortable xmlns:xsi="http://www.w3.org/2001/XMLSchema-instance" xmlns:xsd="http://www.w3.org/2001/XMLSchema">
  <Title>Minhas tarefas</Title>
  <Url>~/wfl/a/t/caixadeentrada.aspx</Url>
  <AutoGenerated>true</AutoGenerated>
  <EntityPermissionId />
  <TemplateId />
  <Details>Listagem com todas as tarefas do workflow pendentes do usuário corrente</Details>
  <Id>WF_TAREFAS_MINHAS</Id>
  <Level>Tecnologia</Level>
  <CodeFile />
  <CodeInherits />
  <Widgets>
    <PageWidgetPortable>
      <Id>WFL_TASKS_INBOX</Id>
      <Title>Minhas tarefas</Title>
      <Order>10</Order>
      <ShowTitle>true</ShowTitle>
      <PortletCssClass />
      <FontIcon />
      <Subtitle />
      <ChromeState>Normal</ChromeState>
      <PortletLayout>Default</PortletLayout>
      <WidgetTypeId>WorkFlowGrid</WidgetTypeId>
      <BootstrapCols>12</BootstrapCols>
      <XmlAttributes><![CDATA[<WorkflowGridAttributes>
  <EntityViewName>Z_WFTAREFAS.INBOX.GRID</EntityViewName>
  <CanDelete>false</CanDelete>
  <CanUpdate>false</CanUpdate>
  <CanInsert>false</CanInsert>
  <SystemInstanceName>WORKFLOW</SystemInstanceName>
  <DefaultFilterName>Título</DefaultFilterName>
  <UserDefinedSelectColumnVisible>false</UserDefinedSelectColumnVisible>
  <Mode>1</Mode>
  <UserDefinedPageSize>10</UserDefinedPageSize>
  <SystemFilterOnly>false</SystemFilterOnly>
  <DisplayRowCommand>true</DisplayRowCommand>
  <CompanyFilterMode>0</CompanyFilterMode>
  <UserDefinedCriteriaWhereClause>@WFL_INBOX</UserDefinedCriteriaWhereClause>
  <FormUrl>~/wfl/a/t/tarefa.aspx</FormUrl>
</WorkflowGridAttributes>]]></XmlAttributes>
      <Level>Tecnologia</Level>
    </PageWidgetPortable>
  </Widgets>
  <Resources />
</PagePortable>